webshooter/__init__.py
webshooter/request.py
webshooter/scraper.py
webshooter/utils.py
webshooter-0.0.2.dist-info/METADATA
webshooter-0.0.2.dist-info/WHEEL
webshooter-0.0.2.dist-info/top_level.txt
webshooter-0.0.2.dist-info/RECORD
